grcriddles
