Metadata-Version: 1.1
Name: grcriddles
Version: 0.1.8
Summary: GRCRiddle - Study and examination of alphabetical and isopsephical riddles of the Ancient Greeks
Home-page: https://github.com/markomanninen/grcriddles
Author: Marko Manninen
Author-email: elonmedia@gmail.com
License: UNKNOWN
Download-URL: https://github.com/markomanninen/grcriddles/archive/v0.1.8.tar.gz
Keywords: python,jupyter notebook,ancient greek,isopsephy,text analysis,natural language processing
Platform: any
Classifier: Development Status :: 3 - Alpha
Classifier: Intended Audience :: Developers
Classifier: License :: OSI Approved :: MIT License
Classifier: Operating System :: OS Independent
Classifier: Programming Language :: Python
Classifier: Topic :: Software Development :: Libraries
